setup.py
mini_mongo_odm/__init__.py
mini_mongo_odm/entity.py
mini_mongo_odm/manager.py
mini_mongo_odm.egg-info/PKG-INFO
mini_mongo_odm.egg-info/SOURCES.txt
mini_mongo_odm.egg-info/dependency_links.txt
mini_mongo_odm.egg-info/not-zip-safe
mini_mongo_odm.egg-info/requires.txt
mini_mongo_odm.egg-info/top_level.txt